{
    "version": "0.1.261",
    "description": "Quarto is an academic, scientific, and technical publishing system built on Pandoc.",
    "homepage": "https://github.com/quarto-dev/quarto-cli/wiki",
    "license": "GPL-2.0-or-later",
    "url": "https://github.com/quarto-dev/quarto-cli/releases/download/v0.1.261/quarto-0.1-win.msi",
    "hash": "f38410762db9f81e6dc5096d8f44d652393a6bfd69b4150d942f6002da018ec5",
    "extract_dir": "Quarto",
    "bin": "bin\\quarto.cmd",
    "checkver": {
        "url": "https://github.com/quarto-dev/quarto-cli/releases/latest",
        "re": "v(?<version>[\\d.]+)/quarto-(?<short>[\\d.]+).*\\.msi"
    },
    "autoupdate": {
        "url": "https://github.com/quarto-dev/quarto-cli/releases/download/v$version/quarto-$matchShort-win.msi"
    }
}
